jcconv.py
jcconv_test.py
setup.py
jcconv.egg-info/PKG-INFO
jcconv.egg-info/SOURCES.txt
jcconv.egg-info/dependency_links.txt
jcconv.egg-info/top_level.txt