Metadata-Version: 1.0
Name: jcconv
Version: 0.1.2
Summary: jcconv "JapaneseCharacterCONVerter", interconvert hiragana, katakana, halfwidth kana
Home-page: http://github.com/taichino/jcconv
Author: Matsumoto Taichi (taichino@gmail.com)
Author-email: taichino@gmail.com
License: MIT License
Keywords: japanese converter,hiragana,katakana,half-width kana
Platform: UNKNOWN
Classifier: Development Status :: 3 - Alpha
Classifier: Intended Audience :: Developers
Classifier: License :: OSI Approved :: MIT License
Classifier: Operating System :: POSIX
Classifier: Programming Language :: Python
Classifier: Topic :: Software Development :: Libraries :: Python Modules
